hello.py
bias_fairness-0.1.1.dist-info/licenses/LICENSE
bias_fairness-0.1.1.dist-info/METADATA
bias_fairness-0.1.1.dist-info/WHEEL
bias_fairness-0.1.1.dist-info/top_level.txt
bias_fairness-0.1.1.dist-info/RECORD
